{"version":1,"resource":"vscode-remote://wsl%2Bubuntu/home/palantir/hwpx/lib/ingestors/docling_ingestor.py","entries":[{"id":"Y9ed.py","source":"Workspace Edit","timestamp":1767690222242},{"id":"q5QH.py","source":"Workspace Edit","timestamp":1767690271030},{"id":"65Qc.py","source":"Workspace Edit","timestamp":1767690322252},{"id":"J45n.py","source":"Workspace Edit","timestamp":1767690401377},{"id":"QTy7.py","source":"Workspace Edit","timestamp":1767690463959},{"id":"UjnC.py","source":"Workspace Edit","timestamp":1767690532683},{"id":"VvUY.py","source":"Workspace Edit","timestamp":1767690579162},{"id":"h893.py","source":"Workspace Edit","timestamp":1767690614879},{"id":"efZ0.py","source":"Workspace Edit","timestamp":1767691110966},{"id":"Vosq.py","source":"Workspace Edit","timestamp":1767691643614},{"id":"xgvG.py","source":"Workspace Edit","timestamp":1767693082766},{"id":"qPIQ.py","source":"Workspace Edit","timestamp":1767693560186},{"id":"rAIp.py","source":"Workspace Edit","timestamp":1767694084686},{"id":"qaWN.py","source":"Workspace Edit","timestamp":1767694117824},{"id":"5eEW.py","source":"Workspace Edit","timestamp":1767694194779},{"id":"k0ip.py","source":"Workspace Edit","timestamp":1767695097647},{"id":"d0kO.py","source":"Workspace Edit","timestamp":1767695327207},{"id":"omgH.py","source":"Workspace Edit","timestamp":1767695374024},{"id":"uaep.py","source":"Workspace Edit","timestamp":1767695441543},{"id":"SL2L.py","source":"Workspace Edit","timestamp":1767695486948},{"id":"8JsL.py","source":"Workspace Edit","timestamp":1767695520773},{"id":"IaAf.py","source":"Workspace Edit","timestamp":1767859531474}]}